bs_icons
