Metadata-Version: 1.1
Name: django-bs-icons
Version: 0.2
Summary: A Django app to easily and cleanly insert Bootstrap icons.
Home-page: https://www.msb.dev
Author: Matthew Smith Burlage
Author-email: matt@msb.dev
License: BSD-3-Clause
Platform: UNKNOWN
Classifier: Environment :: Web Environment
Classifier: Framework :: Django
Classifier: Intended Audience :: Developers
Classifier: License :: OSI Approved :: BSD License
Classifier: Operating System :: OS Independent
Classifier: Programming Language :: Python
Classifier: Programming Language :: Python :: 3
Classifier: Programming Language :: Python :: 3 :: Only
Classifier: Topic :: Internet :: WWW/HTTP
Classifier: Topic :: Internet :: WWW/HTTP :: Dynamic Content
